{
    "display": {
        "icon": {
            "item": "minecraft:wooden_shovel"
        },
        "title": {"translate":"Dague"},
        "description": {"translate":"Doesn't have any friend."},
        "show_toast": false,
        "announce_to_chat": true
    },
    "parent": "att2:collection/weapon_stone/shovel_13",
    "criteria": {
        "wooden_shovel_14": {
            "trigger": "minecraft:inventory_changed",
            "conditions": {
                "items": [
                    {
                    "items": ["minecraft:wooden_shovel"],
                    "nbt": "{display:{Name:\"\\\"§2Dague\\\"\",\"Lore\":[\"{\\\"text\\\":\\\"§7Ne connaît aucun ami.\\\"}\",\"{\\\"text\\\":\\\"§7Doesn't have any friend.\\\"}\"]}}"
                    }
                ]
            }
        }
    }
}
