{
    "display": {
        "icon": {
            "item": "minecraft:spruce_wood"
        },
        "title": {"translate":"Eolorion house expansion"},
        "description": {"translate":"Buy the Eolorion house expansion"},
        "frame": "goal"
    },
    "parent": "att2:adventure/house_eolorion",
    "rewards": {
        "function": "att2:advancement/exploit_25",
        "experience": 10000
                },
    "criteria": {
        "house_eolorion_expansion": {
            "trigger": "minecraft:impossible"
        }
    }
}
