{
    "display": {
        "icon": {
            "item": "minecraft:written_book"
        },
        "title": {"translate":"Your Story!"},
        "description": {"translate":"Write note and make a book."}
    },
    "parent": "att2:adventure/root",
    "rewards": {
        "function": "att2:advancement/exploit_1",
        "experience": 5
                },
    "criteria": {
        "written_book": {
            "trigger": "minecraft:inventory_changed",
            "conditions": {
                "items": [
                    {
                        "items": [
                            "minecraft:written_book"
                        ]
                    }
                ]
            }
        }
    }
}
