{
    "display": {
        "icon": {
            "item": "minecraft:feather"
        },
        "title": {"translate":"Kortaek Panorama"},
        "description": {"translate":"Discover the panorama of Kortaek village"},
        "frame": "goal"
    },
    "parent": "att2:journey/discover_kortaek",
    "rewards": {
        "function": "att2:advancement/exploit_5",
        "experience": 1000
                },
    "criteria": {
        "panorama_kortaek": {
            "trigger": "minecraft:impossible"
        }
    }
}
