{
    "display": {
        "icon": {
            "item": "minecraft:music_disc_pigstep"
        },
        "title": {"translate":"Kert mine Symbol"},
        "description": {"translate":"Discover all Exploration symbols of Kert mine"},
        "frame": "challenge"
    },
    "parent": "att2:journey/discover_kert_mine",
    "rewards": {
        "function": "att2:advancement/exploit_10",
        "experience": 5000
                },
    "criteria": {
        "symbol_kert_mine": {
            "trigger": "minecraft:impossible"
        }
    }
}
