{
    "display": {
        "icon": {
            "item": "minecraft:iron_leggings"
        },
        "title": {"translate":"Couvre-cuisse"},
        "description": {"translate":"Better than a chain mail."},
        "show_toast": false,
        "announce_to_chat": true
    },
    "parent": "att2:collection/armor_iron/leggings_104",
    "criteria": {
        "iron_leggings_111": {
            "trigger": "minecraft:inventory_changed",
            "conditions": {
                "items": [
                    {
                    "items": ["minecraft:iron_leggings"],
                    "nbt": "{display:{Name:\"\\\"§2Couvre-cuisse\\\"\",\"Lore\":[\"{\\\"text\\\":\\\"§7Meilleur qu'une maille.\\\"}\",\"{\\\"text\\\":\\\"§7Better than a chain mail.\\\"}\",\"{\\\"text\\\":\\\"§7STR§a1 §7HAS§c-1\\\"}\"]}}"
                    }
                ]
            }
        }
    }
}
