{
    "display": {
        "icon": {
            "item": "minecraft:item_frame"
        },
        "title": {"translate":"Veteran Elite Eliminator"},
        "description": {"translate":"Kill 10 Veteran Elites"},
        "frame": "goal"
    },
    "parent": "att2:mobskilled/elite_tier8_killed_5",
    "rewards": {
        "function": "att2:advancement/exploit_5",
        "experience": 250
    },
    "criteria": {
        "elite_tier8_killed_10": {
            "trigger": "minecraft:impossible"
        }
    }
}
