{
    "display": {
        "icon": {
            "item": "minecraft:redstone_ore"
        },
        "title": {"translate":"Live forever!"},
        "description": {"translate":"Discover and activate 100 checkpoints"},
        "frame": "goal"
    },
    "parent": "att2:progress/checkpoint_50",
    "rewards": {
        "function": "att2:advancement/exploit_20",
        "experience": 5000
    },
    "criteria": {
        "checkpoint_100": {
            "trigger": "minecraft:impossible"
        }
    }
}
