{
    "display": {
        "icon": {
            "item": "minecraft:leather_helmet"
        },
        "title": {"translate":"Bandana"},
        "description": {"translate":"Not as white as before."},
        "show_toast": false,
        "announce_to_chat": true
    },
    "parent": "att2:collection/armor_leather/helmet_32",
    "criteria": {
        "leather_helmet_33": {
            "trigger": "minecraft:inventory_changed",
            "conditions": {
                "items": [
                    {
                    "items": ["minecraft:leather_helmet"],
                    "nbt": "{display:{Name:\"\\\"ยง2Bandana\\\"\",\"Lore\":[\"{\\\"text\\\":\\\"ยง7Plus aussi blanc qu'avant.\\\"}\",\"{\\\"text\\\":\\\"ยง7Not as white as before.\\\"}\"],color:14540253}}"
                    }
                ]
            }
        }
    }
}
