{
    "display": {
        "icon": {
            "item": "minecraft:target"
        },
        "title": {"translate":"SUPERELITE KILLED"},
        "description": {"translate":"Triggered!"},
        "hidden": true,
        "show_toast": false,
        "announce_to_chat": false
    },
    "parent": "att2:combat/root",
    "rewards": {
        "function": "att2:advancement/test_all/combat/triggerkill_reg2_superelite12"
    },
    "criteria": {
        "triggerkill_reg2_superelite12": {
            "trigger": "minecraft:player_killed_entity",
            "conditions": {
                "entity": {
                    "nbt": "{Tags:[\"SUPER\",\"ELITE12\",\"Reg2\"]}"
                }
            }
        }
    }
}